PandasBasketball/__init__.py
PandasBasketball/errors.py
PandasBasketball/pandasbasketball.py
PandasBasketball/stats.py
PandasBasketball-0.0.1.dist-info/LICENSE
PandasBasketball-0.0.1.dist-info/METADATA
PandasBasketball-0.0.1.dist-info/WHEEL
PandasBasketball-0.0.1.dist-info/top_level.txt
PandasBasketball-0.0.1.dist-info/RECORD
