Metadata-Version: 2.1
Name: PandasBasketball
Version: 0.0.1
Summary: A Python module to scrape data from basketbal-reference.com and convert it to pandas data structures for analysis.
Home-page: https://github.com/alfremedpal/PandasBasketball
Author: Alfredo Medina
Author-email: alfremedpal@gmail.com
License: UNKNOWN
Platform: UNKNOWN
Classifier: Programming Language :: Python :: 3
Classifier: License :: OSI Approved :: MIT License
Classifier: Operating System :: OS Independent
Requires-Dist: requests
Requires-Dist: beautifulsoup4
Requires-Dist: pandas
